xcodex/__init__.py
xcodex/main.py
xcodex/run_tests.py
xcodex/Util/__init__.py
xcodex/Util/check.py
xcodex/Util/create_dodsrc.py
xcodex/Util/create_netrc.py
xcodex/Util/date.py
xcodex/Util/download.py
xcodex/Util/error_handling.py
xcodex/Util/generate_links.py
xcodex/Util/make_Dataframe.py
xcodex/Util/var_imp.py
xcodex/tests/__init__.py
xcodex/tests/test_create_dodsrc.py
xcodex/tests/test_create_netrc.py
xcodex/tests/test_date.py
xcodex/tests/test_download.py
xcodex/tests/test_generate_links.py
xcodex/tests/test_main.py
xcodex/tests/test_make_Dataframe.py
xcodex/tests/test_var_imp.py
xcodex-2.3.4.dist-info/licenses/LICENSE
xcodex-2.3.4.dist-info/METADATA
xcodex-2.3.4.dist-info/WHEEL
xcodex-2.3.4.dist-info/top_level.txt
xcodex-2.3.4.dist-info/RECORD
