Metadata-Version: 2.4
Name: xcodex
Version: 2.3.4
Summary: This package will download and extract daily data of XCO2 from the NASA Goddard Earth Sciences (GES)
Author: henriquefl24@git
Author-email: Henrique Fontellas Laurito <henrique.f.laurito@unesp.br>
Project-URL: Homepage, https://github.com/henriquefl24/xcodex
Project-URL: Bug Tracker, https://github.com/henriquefl24/xcodex/issues
Keywords: python,NASA,GES DISC,XCO2,daily,OCO-2,jupyter notebook,xcodex
Classifier: Development Status :: 5 - Production/Stable
Classifier: Intended Audience :: Developers
Classifier: License :: OSI Approved :: MIT License
Classifier: Programming Language :: Python :: 3.12
Classifier: Operating System :: Unix
Classifier: Operating System :: MacOS :: MacOS X
Classifier: Operating System :: Microsoft :: Windows
Requires-Python: >=3.12
License-File: LICENSE
Requires-Dist: fastparquet
Requires-Dist: h5netcdf
Requires-Dist: jupyter
Requires-Dist: netcdf4
Requires-Dist: numpy
Requires-Dist: openpyxl
Requires-Dist: pandas
Requires-Dist: pyarrow
Requires-Dist: requests
Requires-Dist: scipy
Requires-Dist: setuptools
Requires-Dist: tables
Requires-Dist: tqdm
Requires-Dist: wheel
Requires-Dist: xarray
Dynamic: author
Dynamic: keywords
Dynamic: license-file
Dynamic: requires-dist
Dynamic: requires-python
